s3u/__init__.py
s3u/cli.py
s3u/config.py
s3u/optimizer.py
s3u/permissions.py
s3u/setup.py
s3u/core/__init__.py
s3u/core/browser.py
s3u/core/downloader.py
s3u/core/formatter.py
s3u/core/s3_core.py
s3u/core/uploader.py
s3u/utils/__init__.py
s3u/utils/aws_helpers.py
s3u/utils/progress.py
s3u-0.1.0.dist-info/METADATA
s3u-0.1.0.dist-info/WHEEL
s3u-0.1.0.dist-info/entry_points.txt
s3u-0.1.0.dist-info/top_level.txt
s3u-0.1.0.dist-info/RECORD
