Metadata-Version: 2.2
Name: s3u
Version: 0.1.0
Summary: S3 Upload Utility - Optimize images and upload files to S3
Home-page: https://github.com/danhilse/s3u
Author: Daniel Hilse
Author-email: danhilse@gmail.com
Keywords: s3,upload,aws,utility,images,optimization,cloudfront
Classifier: Development Status :: 4 - Beta
Classifier: Intended Audience :: Developers
Classifier: Programming Language :: Python :: 3
Classifier: Programming Language :: Python :: 3.7
Classifier: Programming Language :: Python :: 3.8
Classifier: Programming Language :: Python :: 3.9
Classifier: License :: OSI Approved :: MIT License
Classifier: Topic :: Utilities
Requires-Python: >=3.7
Requires-Dist: aioboto3
Requires-Dist: pyperclip
Requires-Dist: questionary
Requires-Dist: tqdm
Requires-Dist: boto3
Requires-Dist: pillow
Provides-Extra: dev
Requires-Dist: pytest; extra == "dev"
Requires-Dist: pytest-cov; extra == "dev"
Requires-Dist: flake8; extra == "dev"
Requires-Dist: black; extra == "dev"
Dynamic: author
Dynamic: author-email
Dynamic: classifier
Dynamic: description
Dynamic: description-content-type
Dynamic: home-page
Dynamic: keywords
Dynamic: provides-extra
Dynamic: requires-dist
Dynamic: requires-python
Dynamic: summary
